README.rst
setup.py
pmsensor/__init__.py
pmsensor/co2sensor.py
pmsensor/serial_pm.py
pmsensor.egg-info/PKG-INFO
pmsensor.egg-info/SOURCES.txt
pmsensor.egg-info/dependency_links.txt
pmsensor.egg-info/not-zip-safe
pmsensor.egg-info/requires.txt
pmsensor.egg-info/top_level.txt